Metadata-Version: 2.1
Name: odoo14-addon-l10n_eu_product_adr
Version: 14.0.1.1.1.dev21
Summary: Allows to set appropriate danger class and components
Home-page: https://github.com/OCA/community-data-files
Author: Opener B.V., Camptocamp, Odoo Community Association (OCA)
Author-email: support@odoo-community.org
License: AGPL-3
Classifier: Programming Language :: Python
Classifier: Framework :: Odoo
Classifier: Framework :: Odoo :: 14.0
Classifier: License :: OSI Approved :: GNU Affero General Public License v3
Classifier: Development Status :: 4 - Beta
Requires-Python: >=3.6
Requires-Dist: odoo<14.1dev,>=14.0a
